adamod/__init__.py
adamod/adamod.py
adamod-0.0.3.dist-info/DESCRIPTION.rst
adamod-0.0.3.dist-info/METADATA
adamod-0.0.3.dist-info/RECORD
adamod-0.0.3.dist-info/WHEEL
adamod-0.0.3.dist-info/metadata.json
adamod-0.0.3.dist-info/top_level.txt
