Metadata-Version: 2.0
Name: adamod
Version: 0.0.3
Summary: AdaMod optimization algorithm, build on PyTorch.
Home-page: https://github.com/karrynest/AdaMod
Author: Jianbang Ding
Author-email: jianbangding@pku.edu.cn
License: Apache
Keywords: machine learning,deep learning
Platform: UNKNOWN
Classifier: Intended Audience :: Science/Research
Classifier: Development Status :: 3 - Alpha
Classifier: License :: OSI Approved :: Apache Software License
Classifier: Programming Language :: Python :: 3.6
Classifier: Programming Language :: Python :: 3.7
Classifier: Topic :: Scientific/Engineering :: Artificial Intelligence
Requires-Python: >=3.6.0
Requires-Dist: torch (>=0.4.0)
